aipy/__init__.py
aipy/_deconv.cpython-38-darwin.so
aipy/_dsp.cpython-38-darwin.so
aipy/_miriad.cpython-38-darwin.so
aipy/_version.py
aipy/amp.py
aipy/cal.py
aipy/const.py
aipy/coord.py
aipy/deconv.py
aipy/dsp.py
aipy/fit.py
aipy/healpix.py
aipy/img.py
aipy/interp.py
aipy/map.py
aipy/miriad.py
aipy/phs.py
aipy/pol.py
aipy/rfi.py
aipy/scripting.py
aipy/src.py
aipy/twodgauss.py
aipy/utils.cpython-38-darwin.so
aipy/_common/aipy_compat.h
aipy/_deconv/deconv.cpp
aipy/_dsp/dsp.c
aipy/_dsp/dsp.h
aipy/_dsp/grid/grid.c
aipy/_dsp/grid/grid.h
aipy/_miriad/miriad_wrap.cpp
aipy/_miriad/miriad_wrap.h
aipy/_miriad/mir/args.h
aipy/_miriad/mir/boxes.h
aipy/_miriad/mir/bug.c
aipy/_miriad/mir/calapply.h
aipy/_miriad/mir/caldata.h
aipy/_miriad/mir/caldefs.h
aipy/_miriad/mir/calfit.h
aipy/_miriad/mir/calio.h
aipy/_miriad/mir/calpass.h
aipy/_miriad/mir/calpoly.h
aipy/_miriad/mir/calsubs.h
aipy/_miriad/mir/co.h
aipy/_miriad/mir/ctrl.h
aipy/_miriad/mir/dio.c
aipy/_miriad/mir/fitsio.h
aipy/_miriad/mir/hdtab.h
aipy/_miriad/mir/headio.c
aipy/_miriad/mir/hio.c
aipy/_miriad/mir/hio.h
aipy/_miriad/mir/interface.c
aipy/_miriad/mir/intpio.h
aipy/_miriad/mir/io.h
aipy/_miriad/mir/ivas.h
aipy/_miriad/mir/ivmenu.h
aipy/_miriad/mir/ivofm.h
aipy/_miriad/mir/ivtext.h
aipy/_miriad/mir/jplread.c
aipy/_miriad/mir/key.c
aipy/_miriad/mir/log.h
aipy/_miriad/mir/mapper.h
aipy/_miriad/mir/maskio.c
aipy/_miriad/mir/maxdimc.h
aipy/_miriad/mir/maxnax.h
aipy/_miriad/mir/mc.h
aipy/_miriad/mir/mem.h
aipy/_miriad/mir/mir_io.c
aipy/_miriad/mir/mirconst.h
aipy/_miriad/mir/miriad.h
aipy/_miriad/mir/model.h
aipy/_miriad/mir/modp.h
aipy/_miriad/mir/mostab.h
aipy/_miriad/mir/obspar.h
aipy/_miriad/mir/ofm.h
aipy/_miriad/mir/pack.c
aipy/_miriad/mir/pb.h
aipy/_miriad/mir/pcvt.h
aipy/_miriad/mir/plproc.h
aipy/_miriad/mir/rest.h
aipy/_miriad/mir/scrio.c
aipy/_miriad/mir/select.h
aipy/_miriad/mir/size.h
aipy/_miriad/mir/sma_csub.c
aipy/_miriad/mir/sma_data.h
aipy/_miriad/mir/sma_mirRead.c
aipy/_miriad/mir/sysdep.h
aipy_eovsa-0.1.1.1.dist-info/LICENSE
aipy_eovsa-0.1.1.1.dist-info/LICENSE-GPL
aipy_eovsa-0.1.1.1.dist-info/METADATA
aipy_eovsa-0.1.1.1.dist-info/WHEEL
aipy_eovsa-0.1.1.1.dist-info/top_level.txt
aipy_eovsa-0.1.1.1.dist-info/RECORD
