Metadata-Version: 2.1
Name: aipy-eovsa
Version: 0.1.1.1
Summary: Astronomical Interferometry in PYthon customized for EOVSA
Home-page: https://github.com/ovro-eovsa/aipy-eovsa
Author: Dale Gary, Sijie Yu
Author-email: sijie.yu@njit.edu
License: GPL
Platform: UNKNOWN
Classifier: Development Status :: 5 - Production/Stable
Classifier: Intended Audience :: Science/Research
Classifier: License :: OSI Approved :: GNU General Public License (GPL)
Classifier: Topic :: Scientific/Engineering :: Astronomy
License-File: LICENSE
License-File: LICENSE-GPL
Requires-Dist: astropy (>=3.0)
Requires-Dist: healpy (>=1.11)
Requires-Dist: matplotlib
Requires-Dist: numpy (>=1.2)
Requires-Dist: ephem (>=3.7.3.2)
Requires-Dist: scipy (>=0.19)
Provides-Extra: dev
Requires-Dist: pytest ; extra == 'dev'
Requires-Dist: pytest-cov ; extra == 'dev'
